Workbook

Sheet Quote Calculator
B1: FreightDesk — Offline Mileage & Quote Calculator
B3: INPUTS
B4: Origin ZIP (5-digit) | C4: 30301 | E4: Enter the full 5-digit ZIP. Distance is estimated from the 3-digit ZIP zone (ZIP3) centroid.
B5: Destination ZIP (5-digit) | C5: 07001
B6: Rate per mile ($/mi) | C6: 2.5
B7: Fuel surcharge | C7: 0.18
B8: Minimum charge ($) | C8: 350
B9: Road factor (x straight-line) | C9: 1.2
B11: RESULTS
B12: Origin | C12: =IFERROR(INDEX('ZIP Database'!$B:$B,MATCH($C$23,'ZIP Database'!$A:$A,0))&", "&INDEX('ZIP Database'!$C:$C,MATCH($C$23,'ZIP Database'!$A:$A,0)),"ZIP3 "&$C$23&" not found") -> Atlanta, GA
B13: Destination | C13: =IFERROR(INDEX('ZIP Database'!$B:$B,MATCH($C$26,'ZIP Database'!$A:$A,0))&", "&INDEX('ZIP Database'!$C:$C,MATCH($C$26,'ZIP Database'!$A:$A,0)),"ZIP3 "&$C$26&" not found") -> Newark, NJ
B14: Straight-line miles | C14: =IF(OR($C$24="",$C$27=""),"",ROUND(3958.8*ACOS(MIN(1,SIN(RADIANS($C$24))*SIN(RADIANS($C$27))+COS(RADIANS($C$24))*COS(RADIANS($C$27))*COS(RADIANS($C$28-$C$25)))),1)) -> 739.9
B15: Estimated road miles | C15: =IF($C$14="","",ROUND($C$14*$C$9,0)) -> 888
B16: Line haul ($) | C16: =IF($C$15="","",$C$15*$C$6) -> 2220
B17: Fuel surcharge ($) | C17: =IF($C$16="","",$C$16*$C$7) -> 399.6
B18: Subtotal ($) | C18: =IF($C$16="","",$C$16+$C$17) -> 2619.6
B19: QUOTE ($) | C19: =IF($C$16="","",MAX($C$18,$C$8)) -> 2619.6
B22: Lookup helpers
B23: Origin ZIP3 | C23: =LEFT(TEXT(C4,"00000"),3) -> 303
B24: Origin lat | C24: =IFERROR(INDEX('ZIP Database'!$D:$D,MATCH($C$23,'ZIP Database'!$A:$A,0)),"") -> 33.749
B25: Origin lon | C25: =IFERROR(INDEX('ZIP Database'!$E:$E,MATCH($C$23,'ZIP Database'!$A:$A,0)),"") -> -84.388
B26: Dest ZIP3 | C26: =LEFT(TEXT(C5,"00000"),3) -> 070
B27: Dest lat | C27: =IFERROR(INDEX('ZIP Database'!$D:$D,MATCH($C$26,'ZIP Database'!$A:$A,0)),"") -> 40.7357
B28: Dest lon | C28: =IFERROR(INDEX('ZIP Database'!$E:$E,MATCH($C$26,'ZIP Database'!$A:$A,0)),"") -> -74.1724

Sheet ZIP Database
A1: zip3 | B1: city | C1: state | D1: lat | E1: lon
A2: 005 | B2: Holtsville | C2: NY | D2: 40.81 | E2: -73.05
A3: 006 | B3: San Juan | C3: PR | D3: 18.47 | E3: -66.11
A4: 007 | B4: San Juan | C4: PR | D4: 18.47 | E4: -66.11
A5: 008 | B5: Virgin Islands | C5: VI | D5: 18.34 | E5: -64.93
A6: 009 | B6: San Juan | C6: PR | D6: 18.47 | E6: -66.11
A7: 010 | B7: Springfield | C7: MA | D7: 42.1015 | E7: -72.5898
A8: 011 | B8: Springfield | C8: MA | D8: 42.1015 | E8: -72.5898
A9: 012 | B9: Pittsfield | C9: MA | D9: 42.4501 | E9: -73.2454
A10: 013 | B10: Greenfield | C10: MA | D10: 42.59 | E10: -72.6
A11: 014 | B11: Fitchburg | C11: MA | D11: 42.5834 | E11: -71.8023
A12: 015 | B12: Worcester | C12: MA | D12: 42.2626 | E12: -71.8023
A13: 016 | B13: Worcester | C13: MA | D13: 42.2626 | E13: -71.8023
... A917: 999 | B917: Ketchikan | C917: AK | D917: 55.34 | E917: -131.65

Sheet Batch Quotes
A1: Batch Quotes — paste Origin & Dest ZIPs; leave Rate/Fuel/Min blank to use Quote Calculator defaults
A2: Origin ZIP | B2: Dest ZIP | C2: Origin | D2: Destination | E2: Straight mi | F2: Road mi | G2: Rate/mi | H2: Fuel % | I2: Min $ | J2: QUOTE $
C3: =IF($A3="","",IFERROR(INDEX('ZIP Database'!$B:$B,MATCH(LEFT(TEXT($A3,"00000"),3),'ZIP Database'!$A:$A,0))&", "&INDEX('ZIP Database'!$C:$C,MATCH(LEFT(TEXT($A3,"00000"),3),'ZIP Database'!$A:$A,0)),"not found")) | D3: =IF($B3="","",IFERROR(INDEX('ZIP Database'!$B:$B,MATCH(LEFT(TEXT($B3,"00000"),3),'ZIP Database'!$A:$A,0))&", "&INDEX('ZIP Database'!$C:$C,MATCH(LEFT(TEXT($B3,"00000"),3),'ZIP Database'!$A:$A,0)),"not found")) | E3: =IF(OR($A3="",$B3=""),"",IFERROR(ROUND(3958.8*ACOS(MIN(1,SIN(RADIANS(INDEX('ZIP Database'!$D:$D,MATCH(LEFT(TEXT($A3,"00000"),3),'ZIP Database'!$A:$A,0))))*SIN(RADIANS(INDEX('ZIP Database'!$D:$D,MATCH(LEFT(TEXT($B3,"00000"),3),'ZIP Database'!$A:$A,0))))+COS(RADIANS(INDEX('ZIP Database'!$D:$D,MATCH(LEFT(TEXT($A3,"00000"),3),'ZIP Database'!$A:$A,0))))*COS(RADIANS(INDEX('ZIP Database'!$D:$D,MATCH(LEFT(TEXT($B3,"00000"),3),'ZIP Database'!$A:$A,0))))*COS(RADIANS(INDEX('ZIP Database'!$E:$E,MATCH(LEFT(TEXT($B3,"00000"),3),'ZIP Database'!$A:$A,0))-INDEX('ZIP Database'!$E:$E,MATCH(LEFT(TEXT($A3,"00000"),3),'ZIP Database'!$A:$A,0)))))),1),"not found")) | F3: =IF(OR($E3="",$E3="not found"),"",ROUND($E3*'Quote Calculator'!$C$9,0)) | J3: =IF($F3="","",MAX($F3*IF($G3="",'Quote Calculator'!$C$6,$G3)*(1+IF($H3="",'Quote Calculator'!$C$7,$H3)),IF($I3="",'Quote Calculator'!$C$8,$I3)))
C4: =IF($A4="","",IFERROR(INDEX('ZIP Database'!$B:$B,MATCH(LEFT(TEXT($A4,"00000"),3),'ZIP Database'!$A:$A,0))&", "&INDEX('ZIP Database'!$C:$C,MATCH(LEFT(TEXT($A4,"00000"),3),'ZIP Database'!$A:$A,0)),"not found")) | D4: =IF($B4="","",IFERROR(INDEX('ZIP Database'!$B:$B,MATCH(LEFT(TEXT($B4,"00000"),3),'ZIP Database'!$A:$A,0))&", "&INDEX('ZIP Database'!$C:$C,MATCH(LEFT(TEXT($B4,"00000"),3),'ZIP Database'!$A:$A,0)),"not found")) | E4: =IF(OR($A4="",$B4=""),"",IFERROR(ROUND(3958.8*ACOS(MIN(1,SIN(RADIANS(INDEX('ZIP Database'!$D:$D,MATCH(LEFT(TEXT($A4,"00000"),3),'ZIP Database'!$A:$A,0))))*SIN(RADIANS(INDEX('ZIP Database'!$D:$D,MATCH(LEFT(TEXT($B4,"00000"),3),'ZIP Database'!$A:$A,0))))+COS(RADIANS(INDEX('ZIP Database'!$D:$D,MATCH(LEFT(TEXT($A4,"00000"),3),'ZIP Database'!$A:$A,0))))*COS(RADIANS(INDEX('ZIP Database'!$D:$D,MATCH(LEFT(TEXT($B4,"00000"),3),'ZIP Database'!$A:$A,0))))*COS(RADIANS(INDEX('ZIP Database'!$E:$E,MATCH(LEFT(TEXT($B4,"00000"),3),'ZIP Database'!$A:$A,0))-INDEX('ZIP Database'!$E:$E,MATCH(LEFT(TEXT($A4,"00000"),3),'ZIP Database'!$A:$A,0)))))),1),"not found")) | F4: =IF(OR($E4="",$E4="not found"),"",ROUND($E4*'Quote Calculator'!$C$9,0)) | J4: =IF($F4="","",MAX($F4*IF($G4="",'Quote Calculator'!$C$6,$G4)*(1+IF($H4="",'Quote Calculator'!$C$7,$H4)),IF($I4="",'Quote Calculator'!$C$8,$I4)))
C5: =IF($A5="","",IFERROR(INDEX('ZIP Database'!$B:$B,MATCH(LEFT(TEXT($A5,"00000"),3),'ZIP Database'!$A:$A,0))&", "&INDEX('ZIP Database'!$C:$C,MATCH(LEFT(TEXT($A5,"00000"),3),'ZIP Database'!$A:$A,0)),"not found")) | D5: =IF($B5="","",IFERROR(INDEX('ZIP Database'!$B:$B,MATCH(LEFT(TEXT($B5,"00000"),3),'ZIP Database'!$A:$A,0))&", "&INDEX('ZIP Database'!$C:$C,MATCH(LEFT(TEXT($B5,"00000"),3),'ZIP Database'!$A:$A,0)),"not found")) | E5: =IF(OR($A5="",$B5=""),"",IFERROR(ROUND(3958.8*ACOS(MIN(1,SIN(RADIANS(INDEX('ZIP Database'!$D:$D,MATCH(LEFT(TEXT($A5,"00000"),3),'ZIP Database'!$A:$A,0))))*SIN(RADIANS(INDEX('ZIP Database'!$D:$D,MATCH(LEFT(TEXT($B5,"00000"),3),'ZIP Database'!$A:$A,0))))+COS(RADIANS(INDEX('ZIP Database'!$D:$D,MATCH(LEFT(TEXT($A5,"00000"),3),'ZIP Database'!$A:$A,0))))*COS(RADIANS(INDEX('ZIP Database'!$D:$D,MATCH(LEFT(TEXT($B5,"00000"),3),'ZIP Database'!$A:$A,0))))*COS(RADIANS(INDEX('ZIP Database'!$E:$E,MATCH(LEFT(TEXT($B5,"00000"),3),'ZIP Database'!$A:$A,0))-INDEX('ZIP Database'!$E:$E,MATCH(LEFT(TEXT($A5,"00000"),3),'ZIP Database'!$A:$A,0)))))),1),"not found")) | F5: =IF(OR($E5="",$E5="not found"),"",ROUND($E5*'Quote Calculator'!$C$9,0)) | J5: =IF($F5="","",MAX($F5*IF($G5="",'Quote Calculator'!$C$6,$G5)*(1+IF($H5="",'Quote Calculator'!$C$7,$H5)),IF($I5="",'Quote Calculator'!$C$8,$I5)))
C6: =IF($A6="","",IFERROR(INDEX('ZIP Database'!$B:$B,MATCH(LEFT(TEXT($A6,"00000"),3),'ZIP Database'!$A:$A,0))&", "&INDEX('ZIP Database'!$C:$C,MATCH(LEFT(TEXT($A6,"00000"),3),'ZIP Database'!$A:$A,0)),"not found")) | D6: =IF($B6="","",IFERROR(INDEX('ZIP Database'!$B:$B,MATCH(LEFT(TEXT($B6,"00000"),3),'ZIP Database'!$A:$A,0))&", "&INDEX('ZIP Database'!$C:$C,MATCH(LEFT(TEXT($B6,"00000"),3),'ZIP Database'!$A:$A,0)),"not found")) | E6: =IF(OR($A6="",$B6=""),"",IFERROR(ROUND(3958.8*ACOS(MIN(1,SIN(RADIANS(INDEX('ZIP Database'!$D:$D,MATCH(LEFT(TEXT($A6,"00000"),3),'ZIP Database'!$A:$A,0))))*SIN(RADIANS(INDEX('ZIP Database'!$D:$D,MATCH(LEFT(TEXT($B6,"00000"),3),'ZIP Database'!$A:$A,0))))+COS(RADIANS(INDEX('ZIP Database'!$D:$D,MATCH(LEFT(TEXT($A6,"00000"),3),'ZIP Database'!$A:$A,0))))*COS(RADIANS(INDEX('ZIP Database'!$D:$D,MATCH(LEFT(TEXT($B6,"00000"),3),'ZIP Database'!$A:$A,0))))*COS(RADIANS(INDEX('ZIP Database'!$E:$E,MATCH(LEFT(TEXT($B6,"00000"),3),'ZIP Database'!$A:$A,0))-INDEX('ZIP Database'!$E:$E,MATCH(LEFT(TEXT($A6,"00000"),3),'ZIP Database'!$A:$A,0)))))),1),"not found")) | F6: =IF(OR($E6="",$E6="not found"),"",ROUND($E6*'Quote Calculator'!$C$9,0)) | J6: =IF($F6="","",MAX($F6*IF($G6="",'Quote Calculator'!$C$6,$G6)*(1+IF($H6="",'Quote Calculator'!$C$7,$H6)),IF($I6="",'Quote Calculator'!$C$8,$I6)))
C7: =IF($A7="","",IFERROR(INDEX('ZIP Database'!$B:$B,MATCH(LEFT(TEXT($A7,"00000"),3),'ZIP Database'!$A:$A,0))&", "&INDEX('ZIP Database'!$C:$C,MATCH(LEFT(TEXT($A7,"00000"),3),'ZIP Database'!$A:$A,0)),"not found")) | D7: =IF($B7="","",IFERROR(INDEX('ZIP Database'!$B:$B,MATCH(LEFT(TEXT($B7,"00000"),3),'ZIP Database'!$A:$A,0))&", "&INDEX('ZIP Database'!$C:$C,MATCH(LEFT(TEXT($B7,"00000"),3),'ZIP Database'!$A:$A,0)),"not found")) | E7: =IF(OR($A7="",$B7=""),"",IFERROR(ROUND(3958.8*ACOS(MIN(1,SIN(RADIANS(INDEX('ZIP Database'!$D:$D,MATCH(LEFT(TEXT($A7,"00000"),3),'ZIP Database'!$A:$A,0))))*SIN(RADIANS(INDEX('ZIP Database'!$D:$D,MATCH(LEFT(TEXT($B7,"00000"),3),'ZIP Database'!$A:$A,0))))+COS(RADIANS(INDEX('ZIP Database'!$D:$D,MATCH(LEFT(TEXT($A7,"00000"),3),'ZIP Database'!$A:$A,0))))*COS(RADIANS(INDEX('ZIP Database'!$D:$D,MATCH(LEFT(TEXT($B7,"00000"),3),'ZIP Database'!$A:$A,0))))*COS(RADIANS(INDEX('ZIP Database'!$E:$E,MATCH(LEFT(TEXT($B7,"00000"),3),'ZIP Database'!$A:$A,0))-INDEX('ZIP Database'!$E:$E,MATCH(LEFT(TEXT($A7,"00000"),3),'ZIP Database'!$A:$A,0)))))),1),"not found")) | F7: =IF(OR($E7="",$E7="not found"),"",ROUND($E7*'Quote Calculator'!$C$9,0)) | J7: =IF($F7="","",MAX($F7*IF($G7="",'Quote Calculator'!$C$6,$G7)*(1+IF($H7="",'Quote Calculator'!$C$7,$H7)),IF($I7="",'Quote Calculator'!$C$8,$I7)))
C8: =IF($A8="","",IFERROR(INDEX('ZIP Database'!$B:$B,MATCH(LEFT(TEXT($A8,"00000"),3),'ZIP Database'!$A:$A,0))&", "&INDEX('ZIP Database'!$C:$C,MATCH(LEFT(TEXT($A8,"00000"),3),'ZIP Database'!$A:$A,0)),"not found")) | D8: =IF($B8="","",IFERROR(INDEX('ZIP Database'!$B:$B,MATCH(LEFT(TEXT($B8,"00000"),3),'ZIP Database'!$A:$A,0))&", "&INDEX('ZIP Database'!$C:$C,MATCH(LEFT(TEXT($B8,"00000"),3),'ZIP Database'!$A:$A,0)),"not found")) | E8: =IF(OR($A8="",$B8=""),"",IFERROR(ROUND(3958.8*ACOS(MIN(1,SIN(RADIANS(INDEX('ZIP Database'!$D:$D,MATCH(LEFT(TEXT($A8,"00000"),3),'ZIP Database'!$A:$A,0))))*SIN(RADIANS(INDEX('ZIP Database'!$D:$D,MATCH(LEFT(TEXT($B8,"00000"),3),'ZIP Database'!$A:$A,0))))+COS(RADIANS(INDEX('ZIP Database'!$D:$D,MATCH(LEFT(TEXT($A8,"00000"),3),'ZIP Database'!$A:$A,0))))*COS(RADIANS(INDEX('ZIP Database'!$D:$D,MATCH(LEFT(TEXT($B8,"00000"),3),'ZIP Database'!$A:$A,0))))*COS(RADIANS(INDEX('ZIP Database'!$E:$E,MATCH(LEFT(TEXT($B8,"00000"),3),'ZIP Database'!$A:$A,0))-INDEX('ZIP Database'!$E:$E,MATCH(LEFT(TEXT($A8,"00000"),3),'ZIP Database'!$A:$A,0)))))),1),"not found")) | F8: =IF(OR($E8="",$E8="not found"),"",ROUND($E8*'Quote Calculator'!$C$9,0)) | J8: =IF($F8="","",MAX($F8*IF($G8="",'Quote Calculator'!$C$6,$G8)*(1+IF($H8="",'Quote Calculator'!$C$7,$H8)),IF($I8="",'Quote Calculator'!$C$8,$I8)))
C9: =IF($A9="","",IFERROR(INDEX('ZIP Database'!$B:$B,MATCH(LEFT(TEXT($A9,"00000"),3),'ZIP Database'!$A:$A,0))&", "&INDEX('ZIP Database'!$C:$C,MATCH(LEFT(TEXT($A9,"00000"),3),'ZIP Database'!$A:$A,0)),"not found")) | D9: =IF($B9="","",IFERROR(INDEX('ZIP Database'!$B:$B,MATCH(LEFT(TEXT($B9,"00000"),3),'ZIP Database'!$A:$A,0))&", "&INDEX('ZIP Database'!$C:$C,MATCH(LEFT(TEXT($B9,"00000"),3),'ZIP Database'!$A:$A,0)),"not found")) | E9: =IF(OR($A9="",$B9=""),"",IFERROR(ROUND(3958.8*ACOS(MIN(1,SIN(RADIANS(INDEX('ZIP Database'!$D:$D,MATCH(LEFT(TEXT($A9,"00000"),3),'ZIP Database'!$A:$A,0))))*SIN(RADIANS(INDEX('ZIP Database'!$D:$D,MATCH(LEFT(TEXT($B9,"00000"),3),'ZIP Database'!$A:$A,0))))+COS(RADIANS(INDEX('ZIP Database'!$D:$D,MATCH(LEFT(TEXT($A9,"00000"),3),'ZIP Database'!$A:$A,0))))*COS(RADIANS(INDEX('ZIP Database'!$D:$D,MATCH(LEFT(TEXT($B9,"00000"),3),'ZIP Database'!$A:$A,0))))*COS(RADIANS(INDEX('ZIP Database'!$E:$E,MATCH(LEFT(TEXT($B9,"00000"),3),'ZIP Database'!$A:$A,0))-INDEX('ZIP Database'!$E:$E,MATCH(LEFT(TEXT($A9,"00000"),3),'ZIP Database'!$A:$A,0)))))),1),"not found")) | F9: =IF(OR($E9="",$E9="not found"),"",ROUND($E9*'Quote Calculator'!$C$9,0)) | J9: =IF($F9="","",MAX($F9*IF($G9="",'Quote Calculator'!$C$6,$G9)*(1+IF($H9="",'Quote Calculator'!$C$7,$H9)),IF($I9="",'Quote Calculator'!$C$8,$I9)))
C10: =IF($A10="","",IFERROR(INDEX('ZIP Database'!$B:$B,MATCH(LEFT(TEXT($A10,"00000"),3),'ZIP Database'!$A:$A,0))&", "&INDEX('ZIP Database'!$C:$C,MATCH(LEFT(TEXT($A10,"00000"),3),'ZIP Database'!$A:$A,0)),"not found")) | D10: =IF($B10="","",IFERROR(INDEX('ZIP Database'!$B:$B,MATCH(LEFT(TEXT($B10,"00000"),3),'ZIP Database'!$A:$A,0))&", "&INDEX('ZIP Database'!$C:$C,MATCH(LEFT(TEXT($B10,"00000"),3),'ZIP Database'!$A:$A,0)),"not found")) | E10: =IF(OR($A10="",$B10=""),"",IFERROR(ROUND(3958.8*ACOS(MIN(1,SIN(RADIANS(INDEX('ZIP Database'!$D:$D,MATCH(LEFT(TEXT($A10,"00000"),3),'ZIP Database'!$A:$A,0))))*SIN(RADIANS(INDEX('ZIP Database'!$D:$D,MATCH(LEFT(TEXT($B10,"00000"),3),'ZIP Database'!$A:$A,0))))+COS(RADIANS(INDEX('ZIP Database'!$D:$D,MATCH(LEFT(TEXT($A10,"00000"),3),'ZIP Database'!$A:$A,0))))*COS(RADIANS(INDEX('ZIP Database'!$D:$D,MATCH(LEFT(TEXT($B10,"00000"),3),'ZIP Database'!$A:$A,0))))*COS(RADIANS(INDEX('ZIP Database'!$E:$E,MATCH(LEFT(TEXT($B10,"00000"),3),'ZIP Database'!$A:$A,0))-INDEX('ZIP Database'!$E:$E,MATCH(LEFT(TEXT($A10,"00000"),3),'ZIP Database'!$A:$A,0)))))),1),"not found")) | F10: =IF(OR($E10="",$E10="not found"),"",ROUND($E10*'Quote Calculator'!$C$9,0)) | J10: =IF($F10="","",MAX($F10*IF($G10="",'Quote Calculator'!$C$6,$G10)*(1+IF($H10="",'Quote Calculator'!$C$7,$H10)),IF($I10="",'Quote Calculator'!$C$8,$I10)))
C11: =IF($A11="","",IFERROR(INDEX('ZIP Database'!$B:$B,MATCH(LEFT(TEXT($A11,"00000"),3),'ZIP Database'!$A:$A,0))&", "&INDEX('ZIP Database'!$C:$C,MATCH(LEFT(TEXT($A11,"00000"),3),'ZIP Database'!$A:$A,0)),"not found")) | D11: =IF($B11="","",IFERROR(INDEX('ZIP Database'!$B:$B,MATCH(LEFT(TEXT($B11,"00000"),3),'ZIP Database'!$A:$A,0))&", "&INDEX('ZIP Database'!$C:$C,MATCH(LEFT(TEXT($B11,"00000"),3),'ZIP Database'!$A:$A,0)),"not found")) | E11: =IF(OR($A11="",$B11=""),"",IFERROR(ROUND(3958.8*ACOS(MIN(1,SIN(RADIANS(INDEX('ZIP Database'!$D:$D,MATCH(LEFT(TEXT($A11,"00000"),3),'ZIP Database'!$A:$A,0))))*SIN(RADIANS(INDEX('ZIP Database'!$D:$D,MATCH(LEFT(TEXT($B11,"00000"),3),'ZIP Database'!$A:$A,0))))+COS(RADIANS(INDEX('ZIP Database'!$D:$D,MATCH(LEFT(TEXT($A11,"00000"),3),'ZIP Database'!$A:$A,0))))*COS(RADIANS(INDEX('ZIP Database'!$D:$D,MATCH(LEFT(TEXT($B11,"00000"),3),'ZIP Database'!$A:$A,0))))*COS(RADIANS(INDEX('ZIP Database'!$E:$E,MATCH(LEFT(TEXT($B11,"00000"),3),'ZIP Database'!$A:$A,0))-INDEX('ZIP Database'!$E:$E,MATCH(LEFT(TEXT($A11,"00000"),3),'ZIP Database'!$A:$A,0)))))),1),"not found")) | F11: =IF(OR($E11="",$E11="not found"),"",ROUND($E11*'Quote Calculator'!$C$9,0)) | J11: =IF($F11="","",MAX($F11*IF($G11="",'Quote Calculator'!$C$6,$G11)*(1+IF($H11="",'Quote Calculator'!$C$7,$H11)),IF($I11="",'Quote Calculator'!$C$8,$I11)))
C12: =IF($A12="","",IFERROR(INDEX('ZIP Database'!$B:$B,MATCH(LEFT(TEXT($A12,"00000"),3),'ZIP Database'!$A:$A,0))&", "&INDEX('ZIP Database'!$C:$C,MATCH(LEFT(TEXT($A12,"00000"),3),'ZIP Database'!$A:$A,0)),"not found")) | D12: =IF($B12="","",IFERROR(INDEX('ZIP Database'!$B:$B,MATCH(LEFT(TEXT($B12,"00000"),3),'ZIP Database'!$A:$A,0))&", "&INDEX('ZIP Database'!$C:$C,MATCH(LEFT(TEXT($B12,"00000"),3),'ZIP Database'!$A:$A,0)),"not found")) | E12: =IF(OR($A12="",$B12=""),"",IFERROR(ROUND(3958.8*ACOS(MIN(1,SIN(RADIANS(INDEX('ZIP Database'!$D:$D,MATCH(LEFT(TEXT($A12,"00000"),3),'ZIP Database'!$A:$A,0))))*SIN(RADIANS(INDEX('ZIP Database'!$D:$D,MATCH(LEFT(TEXT($B12,"00000"),3),'ZIP Database'!$A:$A,0))))+COS(RADIANS(INDEX('ZIP Database'!$D:$D,MATCH(LEFT(TEXT($A12,"00000"),3),'ZIP Database'!$A:$A,0))))*COS(RADIANS(INDEX('ZIP Database'!$D:$D,MATCH(LEFT(TEXT($B12,"00000"),3),'ZIP Database'!$A:$A,0))))*COS(RADIANS(INDEX('ZIP Database'!$E:$E,MATCH(LEFT(TEXT($B12,"00000"),3),'ZIP Database'!$A:$A,0))-INDEX('ZIP Database'!$E:$E,MATCH(LEFT(TEXT($A12,"00000"),3),'ZIP Database'!$A:$A,0)))))),1),"not found")) | F12: =IF(OR($E12="",$E12="not found"),"",ROUND($E12*'Quote Calculator'!$C$9,0)) | J12: =IF($F12="","",MAX($F12*IF($G12="",'Quote Calculator'!$C$6,$G12)*(1+IF($H12="",'Quote Calculator'!$C$7,$H12)),IF($I12="",'Quote Calculator'!$C$8,$I12)))
C13: =IF($A13="","",IFERROR(INDEX('ZIP Database'!$B:$B,MATCH(LEFT(TEXT($A13,"00000"),3),'ZIP Database'!$A:$A,0))&", "&INDEX('ZIP Database'!$C:$C,MATCH(LEFT(TEXT($A13,"00000"),3),'ZIP Database'!$A:$A,0)),"not found")) | D13: =IF($B13="","",IFERROR(INDEX('ZIP Database'!$B:$B,MATCH(LEFT(TEXT($B13,"00000"),3),'ZIP Database'!$A:$A,0))&", "&INDEX('ZIP Database'!$C:$C,MATCH(LEFT(TEXT($B13,"00000"),3),'ZIP Database'!$A:$A,0)),"not found")) | E13: =IF(OR($A13="",$B13=""),"",IFERROR(ROUND(3958.8*ACOS(MIN(1,SIN(RADIANS(INDEX('ZIP Database'!$D:$D,MATCH(LEFT(TEXT($A13,"00000"),3),'ZIP Database'!$A:$A,0))))*SIN(RADIANS(INDEX('ZIP Database'!$D:$D,MATCH(LEFT(TEXT($B13,"00000"),3),'ZIP Database'!$A:$A,0))))+COS(RADIANS(INDEX('ZIP Database'!$D:$D,MATCH(LEFT(TEXT($A13,"00000"),3),'ZIP Database'!$A:$A,0))))*COS(RADIANS(INDEX('ZIP Database'!$D:$D,MATCH(LEFT(TEXT($B13,"00000"),3),'ZIP Database'!$A:$A,0))))*COS(RADIANS(INDEX('ZIP Database'!$E:$E,MATCH(LEFT(TEXT($B13,"00000"),3),'ZIP Database'!$A:$A,0))-INDEX('ZIP Database'!$E:$E,MATCH(LEFT(TEXT($A13,"00000"),3),'ZIP Database'!$A:$A,0)))))),1),"not found")) | F13: =IF(OR($E13="",$E13="not found"),"",ROUND($E13*'Quote Calculator'!$C$9,0)) | J13: =IF($F13="","",MAX($F13*IF($G13="",'Quote Calculator'!$C$6,$G13)*(1+IF($H13="",'Quote Calculator'!$C$7,$H13)),IF($I13="",'Quote Calculator'!$C$8,$I13)))
C14: =IF($A14="","",IFERROR(INDEX('ZIP Database'!$B:$B,MATCH(LEFT(TEXT($A14,"00000"),3),'ZIP Database'!$A:$A,0))&", "&INDEX('ZIP Database'!$C:$C,MATCH(LEFT(TEXT($A14,"00000"),3),'ZIP Database'!$A:$A,0)),"not found")) | D14: =IF($B14="","",IFERROR(INDEX('ZIP Database'!$B:$B,MATCH(LEFT(TEXT($B14,"00000"),3),'ZIP Database'!$A:$A,0))&", "&INDEX('ZIP Database'!$C:$C,MATCH(LEFT(TEXT($B14,"00000"),3),'ZIP Database'!$A:$A,0)),"not found")) | E14: =IF(OR($A14="",$B14=""),"",IFERROR(ROUND(3958.8*ACOS(MIN(1,SIN(RADIANS(INDEX('ZIP Database'!$D:$D,MATCH(LEFT(TEXT($A14,"00000"),3),'ZIP Database'!$A:$A,0))))*SIN(RADIANS(INDEX('ZIP Database'!$D:$D,MATCH(LEFT(TEXT($B14,"00000"),3),'ZIP Database'!$A:$A,0))))+COS(RADIANS(INDEX('ZIP Database'!$D:$D,MATCH(LEFT(TEXT($A14,"00000"),3),'ZIP Database'!$A:$A,0))))*COS(RADIANS(INDEX('ZIP Database'!$D:$D,MATCH(LEFT(TEXT($B14,"00000"),3),'ZIP Database'!$A:$A,0))))*COS(RADIANS(INDEX('ZIP Database'!$E:$E,MATCH(LEFT(TEXT($B14,"00000"),3),'ZIP Database'!$A:$A,0))-INDEX('ZIP Database'!$E:$E,MATCH(LEFT(TEXT($A14,"00000"),3),'ZIP Database'!$A:$A,0)))))),1),"not found")) | F14: =IF(OR($E14="",$E14="not found"),"",ROUND($E14*'Quote Calculator'!$C$9,0)) | J14: =IF($F14="","",MAX($F14*IF($G14="",'Quote Calculator'!$C$6,$G14)*(1+IF($H14="",'Quote Calculator'!$C$7,$H14)),IF($I14="",'Quote Calculator'!$C$8,$I14)))
... C52: =IF($A52="","",IFERROR(INDEX('ZIP Database'!$B:$B,MATCH(LEFT(TEXT($A52,"00000"),3),'ZIP Database'!$A:$A,0))&", "&INDEX('ZIP Database'!$C:$C,MATCH(LEFT(TEXT($A52,"00000"),3),'ZIP Database'!$A:$A,0)),"not found")) | D52: =IF($B52="","",IFERROR(INDEX('ZIP Database'!$B:$B,MATCH(LEFT(TEXT($B52,"00000"),3),'ZIP Database'!$A:$A,0))&", "&INDEX('ZIP Database'!$C:$C,MATCH(LEFT(TEXT($B52,"00000"),3),'ZIP Database'!$A:$A,0)),"not found")) | E52: =IF(OR($A52="",$B52=""),"",IFERROR(ROUND(3958.8*ACOS(MIN(1,SIN(RADIANS(INDEX('ZIP Database'!$D:$D,MATCH(LEFT(TEXT($A52,"00000"),3),'ZIP Database'!$A:$A,0))))*SIN(RADIANS(INDEX('ZIP Database'!$D:$D,MATCH(LEFT(TEXT($B52,"00000"),3),'ZIP Database'!$A:$A,0))))+COS(RADIANS(INDEX('ZIP Database'!$D:$D,MATCH(LEFT(TEXT($A52,"00000"),3),'ZIP Database'!$A:$A,0))))*COS(RADIANS(INDEX('ZIP Database'!$D:$D,MATCH(LEFT(TEXT($B52,"00000"),3),'ZIP Database'!$A:$A,0))))*COS(RADIANS(INDEX('ZIP Database'!$E:$E,MATCH(LEFT(TEXT($B52,"00000"),3),'ZIP Database'!$A:$A,0))-INDEX('ZIP Database'!$E:$E,MATCH(LEFT(TEXT($A52,"00000"),3),'ZIP Database'!$A:$A,0)))))),1),"not found")) | F52: =IF(OR($E52="",$E52="not found"),"",ROUND($E52*'Quote Calculator'!$C$9,0)) | J52: =IF($F52="","",MAX($F52*IF($G52="",'Quote Calculator'!$C$6,$G52)*(1+IF($H52="",'Quote Calculator'!$C$7,$H52)),IF($I52="",'Quote Calculator'!$C$8,$I52)))

Sheet Instructions
A1: FreightDesk — Offline Mileage & Quote Calculator
A3: WHAT IT DOES
A4: Estimates driving miles between any two U.S. ZIP codes with no internet, then builds a freight quote.
A5: Works entirely offline — all ZIP coordinates are stored in the "ZIP Database" tab.
A7: HOW TO USE — Single quote (Quote Calculator tab)
A8: 1. Type the Origin and Destination 5-digit ZIP codes in the yellow input cells.
A9: 2. Set your Rate per mile, Fuel surcharge %, and Minimum charge (yellow cells).
A10: 3. Read the QUOTE at the bottom. Road miles and cost update automatically.
A12: HOW TO USE — Many lanes at once (Batch Quotes tab)
A13: Paste Origin and Dest ZIPs down columns A and B. Miles and quote fill in automatically.
A14: Leave Rate/Fuel/Min blank to use the Quote Calculator defaults, or override any row.
A16: HOW THE MILEAGE IS CALCULATED
... A25: Coverage: all 916 in-use continental + AK/HI/PR/VI ZIP3 zones. (P.O.-box-only / military ZIPs excluded.)
